Workbook

Sheet Summary
B2: GBPJPY rules backtest, real OANDA data, Jan 2005 – Oct 2026
B3: Levels drawn from daily candle closes. Fixed risk per trade, spread and slippage included. Every figure below is calculated from the Trades sheet.
B5: Starting balance ($) | C5: 10000 | D5: Inputs: change the yellow cells to see other balances or risk levels.
B6: Risk per trade | C6: 0.005
B8: Headline results
B9: Trades | C9: =COUNT(Trades!$O$2:$O$556) -> 555
B10: Hit target | C10: =COUNTIF(Trades!$N$2:$N$556,"Target")/C9 -> 0.19099099
B11: Average result per trade (R) | C11: =AVERAGE(Trades!$O$2:$O$556) -> 0.21060541
B12: Total result (R) | C12: =SUM(Trades!$O$2:$O$556) -> 116.886
B13: Ending balance ($) | C13: =INDEX(Trades!$Q$2:$Q$556,C9) -> 17547.674
B14: Total return | C14: =C13/C5-1 -> 0.75476744
B15: Return per year (compounded) | C15: =(C13/C5)^(1/((MAX(Trades!$F$2:$F$556)-MIN(Trades!$E$2:$E$556))/365.25))-1 -> 0.026710797
B16: Max drawdown | C16: =MIN(Trades!$S$2:$S$556) -> -0.091916161
B17: Years with a positive result | C17: =COUNTIF('By Year'!$D$5:$D$26,">0")&" of "&COUNT('By Year'!$D$5:$D$26) -> 16 of 22
B18: Worst month | C18: =MIN(Monthly!$C$5:$C$266) -> -0.0251175
B19: Months with a profit | C19: =COUNTIF(Monthly!$C$5:$C$266,">0")/COUNT(Monthly!$C$5:$C$266) -> 0.40310078
B21: Results by period
B22: Period | C22: Trades | D22: Hit target | E22: Avg R per trade | F22: Total R
B23: 2005–2014 | C23: =COUNTIF(Trades!$H$2:$H$556,B23) -> 242 | D23: =COUNTIFS(Trades!$H$2:$H$556,B23,Trades!$N$2:$N$556,"Target")/C23 -> 0.16942149 | E23: =AVERAGEIF(Trades!$H$2:$H$556,B23,Trades!$O$2:$O$556) -> 0.12260992 | F23: =SUMIF(Trades!$H$2:$H$556,B23,Trades!$O$2:$O$556) -> 29.6716
B24: 2015 – Mar 2022 | C24: =COUNTIF(Trades!$H$2:$H$556,B24) -> 181 | D24: =COUNTIFS(Trades!$H$2:$H$556,B24,Trades!$N$2:$N$556,"Target")/C24 -> 0.21546961 | E24: =AVERAGEIF(Trades!$H$2:$H$556,B24,Trades!$O$2:$O$556) -> 0.33547293 | F24: =SUMIF(Trades!$H$2:$H$556,B24,Trades!$O$2:$O$556) -> 60.7206
B25: Mar 2022 – Oct 2026 | C25: =COUNTIF(Trades!$H$2:$H$556,B25) -> 132 | D25: =COUNTIFS(Trades!$H$2:$H$556,B25,Trades!$N$2:$N$556,"Target")/C25 -> 0.1969697 | E25: =AVERAGEIF(Trades!$H$2:$H$556,B25,Trades!$O$2:$O$556) -> 0.20071061 | F25: =SUMIF(Trades!$H$2:$H$556,B25,Trades!$O$2:$O$556) -> 26.4938
B26: All | C26: =SUM(C23:C25) -> 555 | D26: =COUNTIF(Trades!$N$2:$N$556,"Target")/C26 -> 0.19099099 | E26: =AVERAGE(Trades!$O$2:$O$556) -> 0.21060541 | F26: =SUM(Trades!$O$2:$O$556) -> 116.886
B28: Results by setup
B29: Setup | C29: Trades | D29: Hit target | E29: Avg R per trade | F29: Total R
B30: Rejection | C30: =COUNTIF(Trades!$B$2:$B$556,B30) -> 281 | D30: =COUNTIFS(Trades!$B$2:$B$556,B30,Trades!$N$2:$N$556,"Target")/C30 -> 0.22775801 | E30: =AVERAGEIF(Trades!$B$2:$B$556,B30,Trades!$O$2:$O$556) -> 0.36068043 | F30: =SUMIF(Trades!$B$2:$B$556,B30,Trades!$O$2:$O$556) -> 101.3512
B31: Break & retest | C31: =COUNTIF(Trades!$B$2:$B$556,B31) -> 274 | D31: =COUNTIFS(Trades!$B$2:$B$556,B31,Trades!$N$2:$N$556,"Target")/C31 -> 0.15328467 | E31: =AVERAGEIF(Trades!$B$2:$B$556,B31,Trades!$O$2:$O$556) -> 0.05669635 | F31: =SUMIF(Trades!$B$2:$B$556,B31,Trades!$O$2:$O$556) -> 15.5348
B33: Outcomes
B34: Outcome | C34: Trades | D34: Share | E34: Avg R
B35: Target | C35: =COUNTIF(Trades!$N$2:$N$556,B35) -> 106 | D35: =C35/$C$9 -> 0.19099099 | E35: =IFERROR(AVERAGEIF(Trades!$N$2:$N$556,B35,Trades!$O$2:$O$556),0) -> 3.6753538
B36: Stop | C36: =COUNTIF(Trades!$N$2:$N$556,B36) -> 271 | D36: =C36/$C$9 -> 0.48828829 | E36: =IFERROR(AVERAGEIF(Trades!$N$2:$N$556,B36,Trades!$O$2:$O$556),0) -> -1.0123247
B37: Breakeven | C37: =COUNTIF(Trades!$N$2:$N$556,B37) -> 178 | D37: =C37/$C$9 -> 0.32072072 | E37: =IFERROR(AVERAGEIF(Trades!$N$2:$N$556,B37,Trades!$O$2:$O$556),0) -> 0.0092050562
B38: Time stop | C38: =COUNTIF(Trades!$N$2:$N$556,B38) -> 0 | D38: =C38/$C$9 -> 0 | E38: =IFERROR(AVERAGEIF(Trades!$N$2:$N$556,B38,Trades!$O$2:$O$556),0) -> 0
B40: Note: monthly figures sum each month's trade returns, so they can differ slightly from the compounded figures in the chat summary (for example worst month −2.5%).

Sheet Trades
A1: # | B1: Setup | C1: Side | D1: Signal (UTC) | E1: Entry (UTC) | F1: Exit (UTC) | G1: Year | H1: Period | I1: Entry price | J1: Stop | K1: Target | L1: Planned R:R | M1: Risk (pips) | N1: Outcome | O1: Result (R) | P1: Account return | Q1: Equity | R1: Peak equity | S1: Drawdown | T1: Exit month
A2: 1 | B2: Rejection | C2: Buy | D2: 38496.917 | E2: 38497.26 | F2: 38498.635 | G2: =YEAR(E2) -> 2005 | H2: =IF(E2<DATE(2015,1,1),"2005–2014",IF(E2<DATE(2022,3,5),"2015 – Mar 2022","Mar 2022 – Oct 2026")) -> 2005–2014 | I2: 196.555 | J2: 196.035 | K2: 198.572 | L2: 3.88 | M2: 51.98 | N2: Breakeven | O2: 0.0433 | P2: =Summary!$C$6*O2 -> 0.0002165 | Q2: =Summary!$C$5*(1+P2) -> 10002.165 | R2: =MAX(Summary!$C$5,Q2) -> 10002.165 | S2: =Q2/R2-1 -> 0 | T2: =DATE(YEAR(F2),MONTH(F2),1) -> 38473
A3: 2 | B3: Break & retest | C3: Sell | D3: 38498.917 | E3: 38499.094 | F3: 38503.469 | G3: =YEAR(E3) -> 2005 | H3: =IF(E3<DATE(2015,1,1),"2005–2014",IF(E3<DATE(2022,3,5),"2015 – Mar 2022","Mar 2022 – Oct 2026")) -> 2005–2014 | I3: 196.915 | J3: 197.439 | K3: 194.803 | L3: 4.028 | M3: 52.425 | N3: Breakeven | O3: 0.0429 | P3: =Summary!$C$6*O3 -> 0.0002145 | Q3: =Q2*(1+P3) -> 10004.31 | R3: =MAX(R2,Q3) -> 10004.31 | S3: =Q3/R3-1 -> 0 | T3: =DATE(YEAR(F3),MONTH(F3),1) -> 38473
A4: 3 | B4: Rejection | C4: Buy | D4: 38503.917 | E4: 38504.052 | F4: 38504.594 | G4: =YEAR(E4) -> 2005 | H4: =IF(E4<DATE(2015,1,1),"2005–2014",IF(E4<DATE(2022,3,5),"2015 – Mar 2022","Mar 2022 – Oct 2026")) -> 2005–2014 | I4: 196.985 | J4: 196.481 | K4: 198.574 | L4: 3.155 | M4: 50.352 | N4: Stop | O4: -1.0149 | P4: =Summary!$C$6*O4 -> -0.0050745 | Q4: =Q3*(1+P4) -> 9953.5436 | R4: =MAX(R3,Q4) -> 10004.31 | S4: =Q4/R4-1 -> -0.0050745 | T4: =DATE(YEAR(F4),MONTH(F4),1) -> 38504
A5: 4 | B5: Rejection | C5: Buy | D5: 38504.917 | E5: 38505.042 | F5: 38506.021 | G5: =YEAR(E5) -> 2005 | H5: =IF(E5<DATE(2015,1,1),"2005–2014",IF(E5<DATE(2022,3,5),"2015 – Mar 2022","Mar 2022 – Oct 2026")) -> 2005–2014 | I5: 196.805 | J5: 196.303 | K5: 198.574 | L5: 3.526 | M5: 50.167 | N5: Stop | O5: -1.015 | P5: =Summary!$C$6*O5 -> -0.005075 | Q5: =Q4*(1+P5) -> 9903.0294 | R5: =MAX(R4,Q5) -> 10004.31 | S5: =Q5/R5-1 -> -0.010123747 | T5: =DATE(YEAR(F5),MONTH(F5),1) -> 38504
A6: 5 | B6: Break & retest | C6: Sell | D6: 38524.917 | E6: 38527.396 | F6: 38530.052 | G6: =YEAR(E6) -> 2005 | H6: =IF(E6<DATE(2015,1,1),"2005–2014",IF(E6<DATE(2022,3,5),"2015 – Mar 2022","Mar 2022 – Oct 2026")) -> 2005–2014 | I6: 198.912 | J6: 199.44 | K6: 197.242 | L6: 3.165 | M6: 52.752 | N6: Stop | O6: -1.0142 | P6: =Summary!$C$6*O6 -> -0.005071 | Q6: =Q5*(1+P6) -> 9852.8111 | R6: =MAX(R5,Q6) -> 10004.31 | S6: =Q6/R6-1 -> -0.015143409 | T6: =DATE(YEAR(F6),MONTH(F6),1) -> 38504
A7: 6 | B7: Break & retest | C7: Buy | D7: 38530.917 | E7: 38532.531 | F7: 38533.375 | G7: =YEAR(E7) -> 2005 | H7: =IF(E7<DATE(2015,1,1),"2005–2014",IF(E7<DATE(2022,3,5),"2015 – Mar 2022","Mar 2022 – Oct 2026")) -> 2005–2014 | I7: 199.252 | J7: 198.732 | K7: 201.232 | L7: 3.807 | M7: 52.001 | N7: Stop | O7: -1.0144 | P7: =Summary!$C$6*O7 -> -0.005072 | Q7: =Q6*(1+P7) -> 9802.8376 | R7: =MAX(R6,Q7) -> 10004.31 | S7: =Q7/R7-1 -> -0.020138602 | T7: =DATE(YEAR(F7),MONTH(F7),1) -> 38504
A8: 7 | B8: Rejection | C8: Sell | D8: 38538.917 | E8: 38539.406 | F8: 38539.625 | G8: =YEAR(E8) -> 2005 | H8: =IF(E8<DATE(2015,1,1),"2005–2014",IF(E8<DATE(2022,3,5),"2015 – Mar 2022","Mar 2022 – Oct 2026")) -> 2005–2014 | I8: 196.07 | J8: 196.611 | K8: 193.669 | L8: 4.434 | M8: 54.144 | N8: Stop | O8: -1.0139 | P8: =Summary!$C$6*O8 -> -0.0050695 | Q8: =Q7*(1+P8) -> 9753.1422 | R8: =MAX(R7,Q8) -> 10004.31 | S8: =Q8/R8-1 -> -0.025106009 | T8: =DATE(YEAR(F8),MONTH(F8),1) -> 38534
A9: 8 | B9: Rejection | C9: Sell | D9: 38539.917 | E9: 38540.125 | F9: 38540.385 | G9: =YEAR(E9) -> 2005 | H9: =IF(E9<DATE(2015,1,1),"2005–2014",IF(E9<DATE(2022,3,5),"2015 – Mar 2022","Mar 2022 – Oct 2026")) -> 2005–2014 | I9: 196.526 | J9: 197.071 | K9: 194.805 | L9: 3.158 | M9: 54.479 | N9: Target | O9: 3.1582 | P9: =Summary!$C$6*O9 -> 0.015791 | Q9: =Q8*(1+P9) -> 9907.154 | R9: =MAX(R8,Q9) -> 10004.31 | S9: =Q9/R9-1 -> -0.0097114584 | T9: =DATE(YEAR(F9),MONTH(F9),1) -> 38534
A10: 9 | B10: Rejection | C10: Buy | D10: 38547.917 | E10: 38548.271 | F10: 38548.562 | G10: =YEAR(E10) -> 2005 | H10: =IF(E10<DATE(2015,1,1),"2005–2014",IF(E10<DATE(2022,3,5),"2015 – Mar 2022","Mar 2022 – Oct 2026")) -> 2005–2014 | I10: 197.22 | J10: 196.656 | K10: 199.183 | L10: 3.479 | M10: 56.432 | N10: Stop | O10: -1.0133 | P10: =Summary!$C$6*O10 -> -0.0050665 | Q10: =Q9*(1+P10) -> 9856.9594 | R10: =MAX(R9,Q10) -> 10004.31 | S10: =Q10/R10-1 -> -0.014728755 | T10: =DATE(YEAR(F10),MONTH(F10),1) -> 38534
A11: 10 | B11: Break & retest | C11: Sell | D11: 38566.917 | E11: 38567.365 | F11: 38568.406 | G11: =YEAR(E11) -> 2005 | H11: =IF(E11<DATE(2015,1,1),"2005–2014",IF(E11<DATE(2022,3,5),"2015 – Mar 2022","Mar 2022 – Oct 2026")) -> 2005–2014 | I11: 197.984 | J11: 198.615 | K11: 195.057 | L11: 4.635 | M11: 63.145 | N11: Breakeven | O11: 0.0356 | P11: =Summary!$C$6*O11 -> 0.000178 | Q11: =Q10*(1+P11) -> 9858.714 | R11: =MAX(R10,Q11) -> 10004.31 | S11: =Q11/R11-1 -> -0.014553377 | T11: =DATE(YEAR(F11),MONTH(F11),1) -> 38565
A12: 11 | B12: Break & retest | C12: Sell | D12: 38579.917 | E12: 38582.052 | F12: 38586.406 | G12: =YEAR(E12) -> 2005 | H12: =IF(E12<DATE(2015,1,1),"2005–2014",IF(E12<DATE(2022,3,5),"2015 – Mar 2022","Mar 2022 – Oct 2026")) -> 2005–2014 | I12: 198.865 | J12: 199.432 | K12: 196.999 | L12: 3.296 | M12: 56.621 | N12: Target | O12: 3.2963 | P12: =Summary!$C$6*O12 -> 0.0164815 | Q12: =Q11*(1+P12) -> 10021.2 | R12: =MAX(R11,Q12) -> 10021.2 | S12: =Q12/R12-1 -> 0 | T12: =DATE(YEAR(F12),MONTH(F12),1) -> 38565
A13: 12 | B13: Rejection | C13: Buy | D13: 38586.917 | E13: 38587.021 | F13: 38590.344 | G13: =YEAR(E13) -> 2005 | H13: =IF(E13<DATE(2015,1,1),"2005–2014",IF(E13<DATE(2022,3,5),"2015 – Mar 2022","Mar 2022 – Oct 2026")) -> 2005–2014 | I13: 197.636 | J13: 197.088 | K13: 199.489 | L13: 3.385 | M13: 54.755 | N13: Breakeven | O13: 0.0411 | P13: =Summary!$C$6*O13 -> 0.0002055 | Q13: =Q12*(1+P13) -> 10023.26 | R13: =MAX(R12,Q13) -> 10023.26 | S13: =Q13/R13-1 -> 0 | T13: =DATE(YEAR(F13),MONTH(F13),1) -> 38565
A14: 13 | B14: Rejection | C14: Sell | D14: 38594.917 | E14: 38595.146 | F14: 38595.406 | G14: =YEAR(E14) -> 2005 | H14: =IF(E14<DATE(2015,1,1),"2005–2014",IF(E14<DATE(2022,3,5),"2015 – Mar 2022","Mar 2022 – Oct 2026")) -> 2005–2014 | I14: 198.766 | J14: 199.259 | K14: 197.238 | L14: 3.102 | M14: 49.26 | N14: Stop | O14: -1.0152 | P14: =Summary!$C$6*O14 -> -0.005076 | Q14: =Q13*(1+P14) -> 9972.3816 | R14: =MAX(R13,Q14) -> 10023.26 | S14: =Q14/R14-1 -> -0.005076 | T14: =DATE(YEAR(F14),MONTH(F14),1) -> 38565
... A556: 555 | B556: Rejection | C556: Sell | D556: 46286.917 | E556: 46287.25 | F556: 46289.031 | G556: =YEAR(E556) -> 2026 | H556: =IF(E556<DATE(2015,1,1),"2005–2014",IF(E556<DATE(2022,3,5),"2015 – Mar 2022","Mar 2022 – Oct 2026")) -> Mar 2022 – Oct 2026 | I556: 210.731 | J556: 211.345 | K556: 208.858 | L556: 3.051 | M556: 61.392 | N556: Target | O556: 3.0511 | P556: =Summary!$C$6*O556 -> 0.0152555 | Q556: =Q555*(1+P556) -> 17547.674 | R556: =MAX(R555,Q556) -> 17547.674 | S556: =Q556/R556-1 -> 0 | T556: =DATE(YEAR(F556),MONTH(F556),1) -> 46266

Sheet Improvement Tests
B2: Improvement tests: chosen on 2005–2016, checked once on 2017–2026
B3: Source: Claude backtest runs on OANDA GBPJPY 15m data, 16 Oct 2026. Typed values from separate runs. Avg R = average result per trade.
B5: Change tested | C5: Trades 2005–16 | D5: Avg R 2005–16 | E5: Trades 2017–26 | F5: Avg R 2017–26 | G5: Verdict
B6: Current system (keep) | C6: 281 | D6: 0.11 | E6: 274 | F6: 0.314 | G6: Keep
B7: Rejection setup only | C7: 242 | D7: 0.313 | E7: 271 | F7: 0.116 | G7: Rejected: worse after 2016
B8: Rejection only + breakeven at 2R | C8: 230 | D8: 0.386 | E8: 258 | F8: 0.062 | G8: Rejected
B9: Rejection only + no breakeven | C9: 219 | D9: 0.453 | E9: 252 | F9: 0.052 | G9: Rejected: best before 2016, weak after
B10: Rejection only + next target out | C10: 250 | D10: 0.228 | E10: 282 | F10: 0.045 | G10: Rejected
B11: Rejection only + 5-day pause after a stop | C11: 194 | D11: 0.204 | E11: 219 | F11: 0.096 | G11: Rejected
B12: No breakeven + 50-day trend filter | C12: 116 | D12: 0.62 | E12: 146 | F12: -0.012 | G12: Rejected: failed after 2016
B13: No breakeven + skip high volatility | C13: 178 | D13: 0.464 | E13: 213 | F13: 0.094 | G13: Rejected
B14: No breakeven + wick at least half the range | C14: 122 | D14: 0.47 | E14: 141 | F14: 0.151 | G14: Rejected
B15: No breakeven + trend + skip high volatility | C15: 97 | D15: 0.631 | E15: 119 | F15: 0.096 | G15: Rejected
B16: ML filter (logistic regression, top 70%) | C16: 104 | D16: -0.086 | G16: Rejected on training years; not tested further
B18: Result: every change that improved 2005–2016 did worse than the current system on 2017–2026. The improvements fitted the past rather than finding a lasting edge, so the current rules stay unchanged.

Sheet By Year
B2: Result by year (entry year)
B4: Year | C4: Trades | D4: Total R | E4: Avg R | F4: Account return
B5: 2005 | C5: =COUNTIF(Trades!$G$2:$G$556,B5) -> 27 | D5: =SUMIF(Trades!$G$2:$G$556,B5,Trades!$O$2:$O$556) -> 4.3524 | E5: =IFERROR(D5/C5,0) -> 0.1612 | F5: =SUMIF(Trades!$G$2:$G$556,B5,Trades!$P$2:$P$556) -> 0.021762
B6: 2006 | C6: =COUNTIF(Trades!$G$2:$G$556,B6) -> 15 | D6: =SUMIF(Trades!$G$2:$G$556,B6,Trades!$O$2:$O$556) -> 2.8147 | E6: =IFERROR(D6/C6,0) -> 0.18764667 | F6: =SUMIF(Trades!$G$2:$G$556,B6,Trades!$P$2:$P$556) -> 0.0140735
B7: 2007 | C7: =COUNTIF(Trades!$G$2:$G$556,B7) -> 20 | D7: =SUMIF(Trades!$G$2:$G$556,B7,Trades!$O$2:$O$556) -> 8.2222 | E7: =IFERROR(D7/C7,0) -> 0.41111 | F7: =SUMIF(Trades!$G$2:$G$556,B7,Trades!$P$2:$P$556) -> 0.041111
B8: 2008 | C8: =COUNTIF(Trades!$G$2:$G$556,B8) -> 14 | D8: =SUMIF(Trades!$G$2:$G$556,B8,Trades!$O$2:$O$556) -> 2.0439 | E8: =IFERROR(D8/C8,0) -> 0.14599286 | F8: =SUMIF(Trades!$G$2:$G$556,B8,Trades!$P$2:$P$556) -> 0.0102195
B9: 2009 | C9: =COUNTIF(Trades!$G$2:$G$556,B9) -> 26 | D9: =SUMIF(Trades!$G$2:$G$556,B9,Trades!$O$2:$O$556) -> 9.874 | E9: =IFERROR(D9/C9,0) -> 0.37976923 | F9: =SUMIF(Trades!$G$2:$G$556,B9,Trades!$P$2:$P$556) -> 0.04937
B10: 2010 | C10: =COUNTIF(Trades!$G$2:$G$556,B10) -> 41 | D10: =SUMIF(Trades!$G$2:$G$556,B10,Trades!$O$2:$O$556) -> -4.9818 | E10: =IFERROR(D10/C10,0) -> -0.12150732 | F10: =SUMIF(Trades!$G$2:$G$556,B10,Trades!$P$2:$P$556) -> -0.024909
B11: 2011 | C11: =COUNTIF(Trades!$G$2:$G$556,B11) -> 33 | D11: =SUMIF(Trades!$G$2:$G$556,B11,Trades!$O$2:$O$556) -> -3.6609 | E11: =IFERROR(D11/C11,0) -> -0.11093636 | F11: =SUMIF(Trades!$G$2:$G$556,B11,Trades!$P$2:$P$556) -> -0.0183045
B12: 2012 | C12: =COUNTIF(Trades!$G$2:$G$556,B12) -> 25 | D12: =SUMIF(Trades!$G$2:$G$556,B12,Trades!$O$2:$O$556) -> 15.0317 | E12: =IFERROR(D12/C12,0) -> 0.601268 | F12: =SUMIF(Trades!$G$2:$G$556,B12,Trades!$P$2:$P$556) -> 0.0751585
B13: 2013 | C13: =COUNTIF(Trades!$G$2:$G$556,B13) -> 11 | D13: =SUMIF(Trades!$G$2:$G$556,B13,Trades!$O$2:$O$556) -> -6.6213 | E13: =IFERROR(D13/C13,0) -> -0.60193636 | F13: =SUMIF(Trades!$G$2:$G$556,B13,Trades!$P$2:$P$556) -> -0.0331065
B14: 2014 | C14: =COUNTIF(Trades!$G$2:$G$556,B14) -> 30 | D14: =SUMIF(Trades!$G$2:$G$556,B14,Trades!$O$2:$O$556) -> 2.5967 | E14: =IFERROR(D14/C14,0) -> 0.086556667 | F14: =SUMIF(Trades!$G$2:$G$556,B14,Trades!$P$2:$P$556) -> 0.0129835
B15: 2015 | C15: =COUNTIF(Trades!$G$2:$G$556,B15) -> 31 | D15: =SUMIF(Trades!$G$2:$G$556,B15,Trades!$O$2:$O$556) -> -7.3849 | E15: =IFERROR(D15/C15,0) -> -0.23822258 | F15: =SUMIF(Trades!$G$2:$G$556,B15,Trades!$P$2:$P$556) -> -0.0369245
B16: 2016 | C16: =COUNTIF(Trades!$G$2:$G$556,B16) -> 8 | D16: =SUMIF(Trades!$G$2:$G$556,B16,Trades!$O$2:$O$556) -> 8.5041 | E16: =IFERROR(D16/C16,0) -> 1.0630125 | F16: =SUMIF(Trades!$G$2:$G$556,B16,Trades!$P$2:$P$556) -> 0.0425205
... B26: 2026 | C26: =COUNTIF(Trades!$G$2:$G$556,B26) -> 22 | D26: =SUMIF(Trades!$G$2:$G$556,B26,Trades!$O$2:$O$556) -> 6.7627 | E26: =IFERROR(D26/C26,0) -> 0.30739545 | F26: =SUMIF(Trades!$G$2:$G$556,B26,Trades!$P$2:$P$556) -> 0.0338135
B28: 2026 runs to 16 Oct. Account return sums the year's trade returns at the risk set on the Summary sheet.

Sheet Monthly
B2: Account return by month (exit month)
B4: Month | C4: Return | D4: Trades
B5: 38473 | C5: =SUMIF(Trades!$T$2:$T$556,B5,Trades!$P$2:$P$556) -> 0.000431 | D5: =COUNTIF(Trades!$T$2:$T$556,B5) -> 2
B6: 38504 | C6: =SUMIF(Trades!$T$2:$T$556,B6,Trades!$P$2:$P$556) -> -0.0202925 | D6: =COUNTIF(Trades!$T$2:$T$556,B6) -> 4
B7: 38534 | C7: =SUMIF(Trades!$T$2:$T$556,B7,Trades!$P$2:$P$556) -> 0.005655 | D7: =COUNTIF(Trades!$T$2:$T$556,B7) -> 3
B8: 38565 | C8: =SUMIF(Trades!$T$2:$T$556,B8,Trades!$P$2:$P$556) -> 0.011789 | D8: =COUNTIF(Trades!$T$2:$T$556,B8) -> 4
B9: 38596 | C9: =SUMIF(Trades!$T$2:$T$556,B9,Trades!$P$2:$P$556) -> -0.0150185 | D9: =COUNTIF(Trades!$T$2:$T$556,B9) -> 4
B10: 38626 | C10: =SUMIF(Trades!$T$2:$T$556,B10,Trades!$P$2:$P$556) -> 0.030665 | D10: =COUNTIF(Trades!$T$2:$T$556,B10) -> 2
B11: 38657 | C11: =SUMIF(Trades!$T$2:$T$556,B11,Trades!$P$2:$P$556) -> -0.0046255 | D11: =COUNTIF(Trades!$T$2:$T$556,B11) -> 3
B12: 38687 | C12: =SUMIF(Trades!$T$2:$T$556,B12,Trades!$P$2:$P$556) -> 0.0131585 | D12: =COUNTIF(Trades!$T$2:$T$556,B12) -> 5
B13: 38718 | C13: =SUMIF(Trades!$T$2:$T$556,B13,Trades!$P$2:$P$556) -> 0.00016 | D13: =COUNTIF(Trades!$T$2:$T$556,B13) -> 1
B14: 38749 | C14: =SUMIF(Trades!$T$2:$T$556,B14,Trades!$P$2:$P$556) -> 0.0001805 | D14: =COUNTIF(Trades!$T$2:$T$556,B14) -> 1
B15: 38777 | C15: =SUMIF(Trades!$T$2:$T$556,B15,Trades!$P$2:$P$556) -> -0.009376 | D15: =COUNTIF(Trades!$T$2:$T$556,B15) -> 6
B16: 38808 | C16: =SUMIF(Trades!$T$2:$T$556,B16,Trades!$P$2:$P$556) -> 0.021405 | D16: =COUNTIF(Trades!$T$2:$T$556,B16) -> 2
... B262: 46296 | C262: =SUMIF(Trades!$T$2:$T$556,B262,Trades!$P$2:$P$556) -> 0 | D262: =COUNTIF(Trades!$T$2:$T$556,B262) -> 0

Sheet Versions & Stops
B2: Rule versions and stop sizes tested
B3: Source: separate backtest runs by Claude on the same OANDA GBPJPY data, 16 Oct 2026. These are outputs of other runs, so they are typed values, not formulas.
B5: Rule version | C5: Trades | D5: Avg R, all | E5: Avg R 2005–14 | F5: Avg R 2015–Mar 22 | G5: Avg R Mar 22–Oct 26
B6: Levels from wicks (first run) | C6: 525 | D6: 0.084 | E6: 0.22 | F6: -0.062 | G6: -0.015
B7: + newer setup replaces stale order | C7: 693 | D7: 0.055 | E7: 0.153 | F7: -0.072 | G7: 0.022
B8: Levels from closes (main version) | C8: 555 | D8: 0.211 | E8: 0.123 | F8: 0.335 | G8: 0.201
B9: Both fixes | C9: 703 | D9: 0.172 | E9: 0.206 | F9: 0.234 | G9: 0.027
B12: Stop size (main version) | C12: Trades | D12: Avg R, all | E12: Avg R Mar 22–Oct 26 | F12: Stop, typical GBPJPY (pips)
B13: 0.31 × daily ATR | C13: 536 | D13: 0.121 | E13: 0.07 | F13: 41
B14: 0.41 × daily ATR (main) | C14: 555 | D14: 0.211 | E14: 0.201 | F14: 55
B15: 0.51 × daily ATR | C15: 497 | D15: 0.088 | E15: -0.131 | F15: 68
B17: Typical pips use GBPJPY's median daily range of 133.5 pips (2005–2020).

Sheet Rules & Next Steps
B2: Rules tested and what comes next
B4: RULES
B5: Market and data | C5: GBPJPY, OANDA 15-minute prices (mid), Jan 2005 – 16 Oct 2026, downloaded by Solomon from his OANDA demo account.
B6: Daily zone | C6: A level with 3+ touches in the past year, drawn from daily candle opens/closes (not wicks). Zone = level ± 0.3 daily ATR (about ±40 pips).
B7: Rejection setup | C7: Daily candle trades through the level but closes back on the original side with a wick ≥ 1/3 of its range. On 15m: wait for a higher high (lower low for sells) near the zone; limit order at the broken 15m swing.
B8: Break & retest setup | C8: Daily close beyond the far edge of the zone. Limit order back at the level for the retest.
B9: Stop / target | C9: Stop 0.41 daily ATR (~55 pips). Target = nearest daily level giving ≥ 3R and no more than 4 daily ATR away. Otherwise skip.
B10: Management | C10: Breakeven once at +1.2R. 20-day time stop. A newer daily setup does not cancel a pending order in this version. Fixed 0.5% risk.
B11: Costs | C11: 3-pip spread on every trade plus extra slippage on stop exits.
B13: CAVEATS
B14: Rules changed after seeing 2022–2026 | C14: The switch to close-based levels came from Solomon's own description, but it was made after viewing 2022–2026 results. That period is no longer an untouched test.
B15: Sensitive to stop size | C15: A 41-pip stop still works; a 68-pip stop turned 2022–2026 negative (see Versions & Stops).
B16: Modest size of the edge | C16: About +2.7% a year at 0.5% risk. Scaling needs more markets or more risk, and both need their own testing.
B17: Missed trades | C17: The 3 Sep 2026 break-and-retest sell is still not taken. The 3 Aug 2026 rejection buy is taken (entry 211.55) but closed flat after the breakeven move.
B19: NEXT STEPS
B20: 1. Forward test | C20: Run the rules automatically on the OANDA demo account for 2–3 months with no rule changes.
